<Annotataions><image file="0177.jpg"><box height="91" left="1072" top="257" width="1221"><label>What are Beginner Books?</label><segs>1072,257,1275,257,1479,257,1682,257,1886,257,2089,257,2293,257,2293,348,2089,348,1886,348,1682,348,1479,348,1275,348,1072,348</segs><pts x="1120" y="300" /><pts x="1200" y="307" /><pts x="1250" y="307" /><pts x="1296" y="301" /><pts x="1329" y="306" /><pts x="1375" y="310" /><pts x="1426" y="304" /><pts x="1468" y="309" /><pts x="1514" y="309" /><pts x="1555" y="301" /><pts x="1619" y="307" /><pts x="1659" y="312" /><pts x="1706" y="312" /><pts x="1751" y="310" /><pts x="1812" y="320" /><pts x="1859" y="312" /><pts x="1908" y="315" /><pts x="1934" y="307" /><pts x="1975" y="309" /><pts x="2042" y="317" /><pts x="2099" y="320" /><pts x="2148" y="310" /><pts x="2201" y="309" /><pts x="2253" y="309" /></box><box height="62" left="1033" top="363" width="1286"><label>They are the answer to millions of parents and educators who have begged</label><segs>1033,363,1247,363,1461,363,1676,363,1890,363,2104,363,2319,363,2319,425,2104,425,1890,425,1676,425,1461,425,1247,425,1033,425</segs><pts x="1052" y="384" /><pts x="1076" y="392" /><pts x="1098" y="392" /><pts x="1111" y="392" /><pts x="1131" y="389" /><pts x="1147" y="394" /><pts x="1168" y="392" /><pts x="1184" y="394" /><pts x="1195" y="389" /><pts x="1209" y="389" /><pts x="1229" y="389" /><pts x="1246" y="390" /><pts x="1264" y="390" /><pts x="1277" y="392" /><pts x="1298" y="392" /><pts x="1317" y="394" /><pts x="1336" y="389" /><pts x="1360" y="390" /><pts x="1380" y="390" /><pts x="1389" y="390" /><pts x="1404" y="389" /><pts x="1420" y="392" /><pts x="1433" y="394" /><pts x="1458" y="394" /><pts x="1481" y="394" /><pts x="1491" y="392" /><pts x="1502" y="392" /><pts x="1513" y="390" /><pts x="1528" y="395" /><pts x="1545" y="395" /><pts x="1568" y="395" /><pts x="1582" y="395" /><pts x="1600" y="394" /><pts x="1613" y="394" /><pts x="1627" y="395" /><pts x="1640" y="398" /><pts x="1663" y="398" /><pts x="1679" y="397" /><pts x="1696" y="395" /><pts x="1717" y="397" /><pts x="1733" y="394" /><pts x="1749" y="394" /><pts x="1767" y="398" /><pts x="1778" y="400" /><pts x="1799" y="397" /><pts x="1822" y="397" /><pts x="1838" y="398" /><pts x="1856" y="397" /><pts x="1870" y="397" /><pts x="1891" y="398" /><pts x="1913" y="397" /><pts x="1933" y="398" /><pts x="1947" y="398" /><pts x="1963" y="398" /><pts x="1981" y="400" /><pts x="2000" y="400" /><pts x="2015" y="400" /><pts x="2034" y="398" /><pts x="2053" y="400" /><pts x="2076" y="395" /><pts x="2093" y="398" /><pts x="2111" y="398" /><pts x="2134" y="403" /><pts x="2153" y="398" /><pts x="2174" y="400" /><pts x="2187" y="402" /><pts x="2208" y="403" /><pts x="2225" y="402" /><pts x="2245" y="403" /><pts x="2264" y="402" /><pts x="2280" y="405" /><pts x="2296" y="402" /></box><box height="47" left="1030" top="415" width="1281"><label>for books that beginning readers can really enjoy as well as read by them-</label><segs>1030,415,1243,415,1457,415,1670,415,1884,415,2097,415,2311,415,2311,462,2097,462,1884,462,1670,462,1457,462,1243,462,1030,462</segs><pts x="1039" y="434" /><pts x="1057" y="439" /><pts x="1074" y="434" /><pts x="1092" y="432" /><pts x="1106" y="437" /><pts x="1130" y="439" /><pts x="1148" y="437" /><pts x="1169" y="436" /><pts x="1182" y="436" /><pts x="1202" y="437" /><pts x="1212" y="436" /><pts x="1231" y="437" /><pts x="1252" y="436" /><pts x="1268" y="434" /><pts x="1284" y="434" /><pts x="1300" y="434" /><pts x="1324" y="436" /><pts x="1337" y="437" /><pts x="1356" y="439" /><pts x="1372" y="437" /><pts x="1393" y="437" /><pts x="1407" y="440" /><pts x="1427" y="440" /><pts x="1443" y="442" /><pts x="1460" y="439" /><pts x="1479" y="439" /><pts x="1497" y="444" /><pts x="1510" y="442" /><pts x="1534" y="442" /><pts x="1550" y="440" /><pts x="1569" y="440" /><pts x="1582" y="440" /><pts x="1596" y="442" /><pts x="1614" y="440" /><pts x="1630" y="445" /><pts x="1651" y="440" /><pts x="1668" y="440" /><pts x="1689" y="440" /><pts x="1707" y="444" /><pts x="1721" y="442" /><pts x="1736" y="440" /><pts x="1745" y="445" /><pts x="1761" y="444" /><pts x="1779" y="439" /><pts x="1796" y="444" /><pts x="1817" y="447" /><pts x="1837" y="444" /><pts x="1851" y="445" /><pts x="1870" y="445" /><pts x="1885" y="444" /><pts x="1901" y="445" /><pts x="1920" y="449" /><pts x="1934" y="447" /><pts x="1957" y="445" /><pts x="1977" y="449" /><pts x="1990" y="445" /><pts x="2000" y="445" /><pts x="2013" y="447" /><pts x="2029" y="447" /><pts x="2049" y="447" /><pts x="2061" y="445" /><pts x="2080" y="450" /><pts x="2093" y="449" /><pts x="2110" y="450" /><pts x="2130" y="449" /><pts x="2149" y="449" /><pts x="2166" y="449" /><pts x="2192" y="449" /><pts x="2210" y="450" /><pts x="2222" y="450" /><pts x="2234" y="449" /><pts x="2258" y="449" /><pts x="2285" y="450" /><pts x="2302" y="450" /></box><box height="46" left="1441" top="470" width="875"><label>selves. They are the products of the fertile imagina-</label><segs>1441,470,1586,470,1732,470,1878,470,2024,470,2170,470,2316,470,2316,516,2170,516,2024,516,1878,516,1732,516,1586,516,1441,516</segs><pts x="1451" y="485" /><pts x="1468" y="488" /><pts x="1483" y="485" /><pts x="1498" y="485" /><pts x="1517" y="485" /><pts x="1535" y="487" /><pts x="1548" y="494" /><pts x="1555" y="489" /><pts x="1574" y="485" /><pts x="1599" y="487" /><pts x="1622" y="489" /><pts x="1636" y="487" /><pts x="1652" y="489" /><pts x="1668" y="488" /><pts x="1686" y="487" /><pts x="1703" y="487" /><pts x="1717" y="488" /><pts x="1725" y="488" /><pts x="1741" y="488" /><pts x="1766" y="491" /><pts x="1783" y="489" /><pts x="1796" y="488" /><pts x="1819" y="489" /><pts x="1833" y="489" /><pts x="1852" y="491" /><pts x="1876" y="491" /><pts x="1896" y="489" /><pts x="1911" y="488" /><pts x="1929" y="488" /><pts x="1940" y="490" /><pts x="1955" y="490" /><pts x="1970" y="493" /><pts x="1983" y="490" /><pts x="1995" y="489" /><pts x="2015" y="493" /><pts x="2030" y="493" /><pts x="2049" y="494" /><pts x="2060" y="495" /><pts x="2075" y="497" /><pts x="2093" y="494" /><pts x="2109" y="490" /><pts x="2119" y="491" /><pts x="2132" y="494" /><pts x="2143" y="494" /><pts x="2163" y="494" /><pts x="2172" y="496" /><pts x="2193" y="496" /><pts x="2219" y="495" /><pts x="2239" y="498" /><pts x="2254" y="494" /><pts x="2272" y="496" /><pts x="2293" y="497" /><pts x="2309" y="498" /></box><box height="42" left="1438" top="519" width="883"><label>tions and drawing boards of some of our most gifted</label><segs>1438,519,1585,519,1732,519,1879,519,2026,519,2173,519,2321,519,2321,561,2173,561,2026,561,1879,561,1732,561,1585,561,1438,561</segs><pts x="1450" y="535" /><pts x="1464" y="535" /><pts x="1482" y="536" /><pts x="1498" y="538" /><pts x="1518" y="537" /><pts x="1529" y="535" /><pts x="1549" y="536" /><pts x="1569" y="538" /><pts x="1589" y="538" /><pts x="1603" y="536" /><pts x="1619" y="536" /><pts x="1641" y="535" /><pts x="1660" y="537" /><pts x="1683" y="533" /><pts x="1706" y="535" /><pts x="1720" y="536" /><pts x="1741" y="538" /><pts x="1755" y="536" /><pts x="1770" y="534" /><pts x="1787" y="535" /><pts x="1812" y="536" /><pts x="1833" y="535" /><pts x="1846" y="536" /><pts x="1866" y="536" /><pts x="1878" y="536" /><pts x="1892" y="537" /><pts x="1910" y="535" /><pts x="1921" y="536" /><pts x="1932" y="537" /><pts x="1950" y="538" /><pts x="1974" y="538" /><pts x="2000" y="538" /><pts x="2013" y="540" /><pts x="2027" y="537" /><pts x="2043" y="537" /><pts x="2056" y="538" /><pts x="2069" y="540" /><pts x="2091" y="540" /><pts x="2112" y="540" /><pts x="2124" y="540" /><pts x="2141" y="540" /><pts x="2169" y="541" /><pts x="2185" y="538" /><pts x="2199" y="541" /><pts x="2213" y="542" /><pts x="2226" y="542" /><pts x="2242" y="542" /><pts x="2256" y="541" /><pts x="2270" y="543" /><pts x="2281" y="542" /><pts x="2301" y="544" /></box><box height="39" left="1438" top="566" width="883"><label>writers and artists. Any child who reads a BEGINNER</label><segs>1438,566,1585,566,1732,566,1879,566,2026,566,2173,566,2321,566,2321,605,2173,605,2026,605,1879,605,1732,605,1585,605,1438,605</segs><pts x="1458" y="579" /><pts x="1479" y="579" /><pts x="1493" y="580" /><pts x="1506" y="579" /><pts x="1522" y="578" /><pts x="1539" y="578" /><pts x="1556" y="578" /><pts x="1562" y="583" /><pts x="1577" y="583" /><pts x="1600" y="582" /><pts x="1619" y="581" /><pts x="1636" y="582" /><pts x="1652" y="582" /><pts x="1668" y="581" /><pts x="1681" y="581" /><pts x="1700" y="583" /><pts x="1709" y="583" /><pts x="1727" y="579" /><pts x="1739" y="581" /><pts x="1755" y="592" /><pts x="1762" y="582" /><pts x="1779" y="584" /><pts x="1805" y="581" /><pts x="1828" y="583" /><pts x="1841" y="586" /><pts x="1855" y="586" /><pts x="1873" y="586" /><pts x="1890" y="586" /><pts x="1901" y="582" /><pts x="1915" y="583" /><pts x="1930" y="586" /><pts x="1952" y="583" /><pts x="1976" y="586" /><pts x="1995" y="588" /><pts x="2008" y="584" /><pts x="2021" y="587" /><pts x="2042" y="587" /><pts x="2059" y="586" /><pts x="2075" y="584" /><pts x="2096" y="586" /><pts x="2110" y="586" /><pts x="2123" y="589" /><pts x="2136" y="587" /><pts x="2154" y="587" /><pts x="2175" y="587" /><pts x="2196" y="587" /><pts x="2216" y="589" /><pts x="2239" y="588" /><pts x="2262" y="589" /><pts x="2286" y="590" /><pts x="2303" y="590" /></box><box height="49" left="1441" top="649" width="880"><label>words are not only fun to read but they can tell a</label><segs>1441,649,1587,649,1734,649,1881,649,2027,649,2174,649,2321,649,2321,698,2174,698,2027,698,1881,698,1734,698,1587,698,1441,698</segs><pts x="1449" y="673" /><pts x="1478" y="673" /><pts x="1494" y="672" /><pts x="1514" y="670" /><pts x="1532" y="674" /><pts x="1548" y="673" /><pts x="1567" y="674" /><pts x="1586" y="672" /><pts x="1601" y="673" /><pts x="1618" y="673" /><pts x="1636" y="673" /><pts x="1659" y="674" /><pts x="1672" y="673" /><pts x="1685" y="673" /><pts x="1702" y="675" /><pts x="1729" y="677" /><pts x="1744" y="672" /><pts x="1761" y="673" /><pts x="1772" y="674" /><pts x="1794" y="674" /><pts x="1810" y="675" /><pts x="1831" y="676" /><pts x="1849" y="674" /><pts x="1860" y="675" /><pts x="1881" y="679" /><pts x="1899" y="676" /><pts x="1916" y="677" /><pts x="1931" y="679" /><pts x="1950" y="680" /><pts x="1966" y="680" /><pts x="1985" y="677" /><pts x="2009" y="680" /><pts x="2022" y="680" /><pts x="2044" y="681" /><pts x="2061" y="681" /><pts x="2073" y="681" /><pts x="2087" y="682" /><pts x="2110" y="680" /><pts x="2131" y="677" /><pts x="2148" y="679" /><pts x="2167" y="682" /><pts x="2183" y="681" /><pts x="2203" y="681" /><pts x="2223" y="680" /><pts x="2236" y="679" /><pts x="2253" y="679" /><pts x="2270" y="680" /><pts x="2280" y="680" /><pts x="2294" y="686" /><pts x="2306" y="683" /></box><box height="52" left="1493" top="750" width="831"><label>BEGIN YOUR CHILD'S LIBRARY WITH</label><segs>1493,750,1631,750,1770,750,1908,750,2047,750,2185,750,2324,750,2324,802,2185,802,2047,802,1908,802,1770,802,1631,802,1493,802</segs><pts x="1509" y="770" /><pts x="1539" y="770" /><pts x="1568" y="771" /><pts x="1593" y="772" /><pts x="1617" y="773" /><pts x="1636" y="773" /><pts x="1667" y="772" /><pts x="1698" y="774" /><pts x="1723" y="773" /><pts x="1760" y="774" /><pts x="1779" y="777" /><pts x="1809" y="776" /><pts x="1839" y="779" /><pts x="1863" y="777" /><pts x="1884" y="776" /><pts x="1917" y="773" /><pts x="1934" y="763" /><pts x="1949" y="776" /><pts x="1977" y="778" /><pts x="1999" y="778" /><pts x="2020" y="778" /><pts x="2043" y="779" /><pts x="2076" y="777" /><pts x="2101" y="779" /><pts x="2137" y="777" /><pts x="2168" y="780" /><pts x="2190" y="779" /><pts x="2227" y="780" /><pts x="2253" y="780" /><pts x="2274" y="780" /><pts x="2299" y="781" /></box><box height="45" left="1438" top="799" width="579"><label>THESE BEGINNER BOOKS!</label><segs>1438,799,1534,799,1631,799,1727,799,1824,799,1920,799,2017,799,2017,844,1920,844,1824,844,1727,844,1631,844,1534,844,1438,844</segs><pts x="1451" y="817" /><pts x="1482" y="822" /><pts x="1510" y="816" /><pts x="1539" y="819" /><pts x="1561" y="820" /><pts x="1589" y="822" /><pts x="1615" y="824" /><pts x="1645" y="824" /><pts x="1673" y="822" /><pts x="1696" y="821" /><pts x="1721" y="823" /><pts x="1748" y="823" /><pts x="1780" y="822" /><pts x="1807" y="822" /><pts x="1836" y="823" /><pts x="1863" y="825" /><pts x="1888" y="822" /><pts x="1917" y="820" /><pts x="1945" y="824" /><pts x="1984" y="825" /><pts x="2005" y="826" /></box><box height="36" left="1823" top="924" width="368"><label>President of Random House</label><segs>1823,924,1884,924,1945,924,2007,924,2068,924,2129,924,2191,924,2191,960,2129,960,2068,960,2007,960,1945,960,1884,960,1823,960</segs><pts x="1832" y="941" /><pts x="1846" y="943" /><pts x="1861" y="942" /><pts x="1873" y="943" /><pts x="1882" y="943" /><pts x="1892" y="943" /><pts x="1908" y="943" /><pts x="1925" y="943" /><pts x="1936" y="942" /><pts x="1949" y="944" /><pts x="1960" y="945" /><pts x="1972" y="942" /><pts x="1981" y="943" /><pts x="1997" y="942" /><pts x="2017" y="947" /><pts x="2033" y="946" /><pts x="2047" y="947" /><pts x="2066" y="947" /><pts x="2086" y="947" /><pts x="2102" y="947" /><pts x="2118" y="944" /><pts x="2140" y="947" /><pts x="2153" y="947" /><pts x="2167" y="946" /><pts x="2182" y="949" /></box><box height="81" left="1181" top="1207" width="652"><label>1. The Cat in the Hat</label><segs>1181,1207,1289,1207,1398,1207,1507,1207,1615,1207,1724,1207,1833,1207,1833,1288,1724,1288,1615,1288,1507,1288,1398,1288,1289,1288,1181,1288</segs><pts x="1211" y="1238" /><pts x="1222" y="1255" /><pts x="1234" y="1244" /><pts x="1274" y="1238" /><pts x="1304" y="1242" /><pts x="1337" y="1246" /><pts x="1378" y="1247" /><pts x="1410" y="1247" /><pts x="1448" y="1252" /><pts x="1480" y="1252" /><pts x="1498" y="1252" /><pts x="1524" y="1252" /><pts x="1542" y="1251" /><pts x="1581" y="1249" /><pts x="1599" y="1247" /><pts x="1636" y="1252" /><pts x="1678" y="1256" /><pts x="1706" y="1252" /><pts x="1736" y="1256" /><pts x="1784" y="1256" /><pts x="1810" y="1252" /></box><box height="86" left="1189" top="1303" width="992"><label>2. The Cat in the Hat Comes Back</label><segs>1189,1303,1354,1303,1519,1303,1685,1303,1850,1303,2015,1303,2181,1303,2181,1389,2015,1389,1850,1389,1685,1389,1519,1389,1354,1389,1189,1389</segs><pts x="1203" y="1334" /><pts x="1231" y="1357" /><pts x="1243" y="1342" /><pts x="1275" y="1332" /><pts x="1311" y="1335" /><pts x="1353" y="1345" /><pts x="1376" y="1342" /><pts x="1408" y="1342" /><pts x="1448" y="1349" /><pts x="1469" y="1339" /><pts x="1491" y="1345" /><pts x="1510" y="1345" /><pts x="1539" y="1345" /><pts x="1570" y="1339" /><pts x="1594" y="1339" /><pts x="1621" y="1339" /><pts x="1668" y="1345" /><pts x="1692" y="1344" /><pts x="1722" y="1349" /><pts x="1759" y="1347" /><pts x="1782" y="1342" /><pts x="1809" y="1346" /><pts x="1838" y="1341" /><pts x="1875" y="1344" /><pts x="1911" y="1345" /><pts x="1951" y="1344" /><pts x="1993" y="1346" /><pts x="2012" y="1346" /><pts x="2043" y="1345" /><pts x="2088" y="1346" /><pts x="2116" y="1345" /><pts x="2156" y="1349" /></box><box height="75" left="1189" top="1405" width="514"><label>3. A Fly Went By</label><segs>1189,1405,1274,1405,1360,1405,1446,1405,1531,1405,1617,1405,1703,1405,1703,1480,1617,1480,1531,1480,1446,1480,1360,1480,1274,1480,1189,1480</segs><pts x="1205" y="1428" /><pts x="1231" y="1448" /><pts x="1256" y="1432" /><pts x="1287" y="1438" /><pts x="1332" y="1432" /><pts x="1357" y="1434" /><pts x="1385" y="1437" /><pts x="1410" y="1439" /><pts x="1433" y="1439" /><pts x="1476" y="1432" /><pts x="1517" y="1437" /><pts x="1550" y="1437" /><pts x="1575" y="1436" /><pts x="1596" y="1434" /><pts x="1627" y="1434" /><pts x="1676" y="1444" /></box><box height="77" left="1184" top="1496" width="506"><label>4. The Big Jump</label><segs>1184,1496,1268,1496,1352,1496,1437,1496,1521,1496,1605,1496,1690,1496,1690,1573,1605,1573,1521,1573,1437,1573,1352,1573,1268,1573,1184,1573</segs><pts x="1206" y="1523" /><pts x="1226" y="1537" /><pts x="1248" y="1527" /><pts x="1283" y="1521" /><pts x="1309" y="1521" /><pts x="1346" y="1525" /><pts x="1382" y="1525" /><pts x="1412" y="1523" /><pts x="1451" y="1527" /><pts x="1471" y="1531" /><pts x="1504" y="1529" /><pts x="1536" y="1524" /><pts x="1569" y="1526" /><pts x="1618" y="1528" /><pts x="1661" y="1532" /></box><box height="73" left="1181" top="1581" width="636"><label>5. A Big Ball of String</label><segs>1181,1581,1287,1581,1393,1581,1499,1581,1605,1581,1711,1581,1817,1581,1817,1654,1711,1654,1605,1654,1499,1654,1393,1654,1287,1654,1181,1654</segs><pts x="1201" y="1609" /><pts x="1224" y="1627" /><pts x="1243" y="1614" /><pts x="1285" y="1611" /><pts x="1319" y="1608" /><pts x="1349" y="1604" /><pts x="1378" y="1605" /><pts x="1402" y="1607" /><pts x="1432" y="1610" /><pts x="1466" y="1605" /><pts x="1505" y="1609" /><pts x="1531" y="1605" /><pts x="1548" y="1606" /><pts x="1559" y="1609" /><pts x="1579" y="1608" /><pts x="1607" y="1604" /><pts x="1636" y="1608" /><pts x="1663" y="1602" /><pts x="1694" y="1607" /><pts x="1716" y="1607" /><pts x="1738" y="1606" /><pts x="1764" y="1609" /><pts x="1792" y="1609" /></box><box height="70" left="1181" top="1664" width="683"><label>6. Sam and the Firefly</label><segs>1181,1664,1294,1664,1408,1664,1522,1664,1636,1664,1750,1664,1864,1664,1864,1734,1750,1734,1636,1734,1522,1734,1408,1734,1294,1734,1181,1734</segs><pts x="1198" y="1699" /><pts x="1222" y="1708" /><pts x="1242" y="1698" /><pts x="1284" y="1693" /><pts x="1321" y="1697" /><pts x="1367" y="1695" /><pts x="1409" y="1700" /><pts x="1448" y="1699" /><pts x="1481" y="1695" /><pts x="1517" y="1692" /><pts x="1545" y="1692" /><pts x="1570" y="1686" /><pts x="1599" y="1690" /><pts x="1633" y="1693" /><pts x="1665" y="1691" /><pts x="1687" y="1691" /><pts x="1718" y="1695" /><pts x="1738" y="1694" /><pts x="1758" y="1695" /><pts x="1786" y="1694" /><pts x="1814" y="1694" /><pts x="1841" y="1699" /></box><box height="59" left="1384" top="1753" width="652"><label>AT ALL BOOK STORES $1.95</label><segs>1384,1753,1492,1753,1601,1753,1710,1753,1818,1753,1927,1753,2036,1753,2036,1812,1927,1812,1818,1812,1710,1812,1601,1812,1492,1812,1384,1812</segs><pts x="1406" y="1779" /><pts x="1430" y="1777" /><pts x="1450" y="1777" /><pts x="1487" y="1780" /><pts x="1514" y="1775" /><pts x="1546" y="1777" /><pts x="1569" y="1778" /><pts x="1595" y="1774" /><pts x="1625" y="1777" /><pts x="1659" y="1780" /><pts x="1691" y="1779" /><pts x="1722" y="1776" /><pts x="1745" y="1775" /><pts x="1770" y="1780" /><pts x="1793" y="1780" /><pts x="1821" y="1777" /><pts x="1855" y="1782" /><pts x="1877" y="1780" /><pts x="1899" y="1780" /><pts x="1919" y="1763" /><pts x="1943" y="1775" /><pts x="1951" y="1795" /><pts x="1970" y="1778" /><pts x="2006" y="1775" /></box><box height="86" left="1030" top="480" width="325"><label>I CAN READ IT</label><segs>1030,545,1083,501,1137,483,1191,480,1245,485,1300,506,1355,540,1329,561,1282,532,1237,519,1191,514,1146,522,1101,540,1056,566</segs><pts x="1058" y="549" /><pts x="1066" y="540" /><pts x="1093" y="524" /><pts x="1112" y="515" /><pts x="1143" y="501" /><pts x="1170" y="497" /><pts x="1191" y="495" /><pts x="1222" y="497" /><pts x="1247" y="502" /><pts x="1279" y="516" /><pts x="1301" y="523" /><pts x="1310" y="532" /><pts x="1327" y="547" /></box><box height="112" left="997" top="755" width="350"><label>ALL BY MYSELF</label><segs>1033,755,1080,794,1129,815,1178,831,1228,820,1278,792,1329,766,1347,807,1286,844,1227,867,1169,864,1111,854,1053,831,997,792</segs><pts x="1035" y="785" /><pts x="1049" y="798" /><pts x="1068" y="814" /><pts x="1085" y="826" /><pts x="1108" y="836" /><pts x="1134" y="845" /><pts x="1154" y="847" /><pts x="1185" y="850" /><pts x="1220" y="846" /><pts x="1251" y="837" /><pts x="1277" y="825" /><pts x="1297" y="815" /><pts x="1316" y="795" /></box><box height="65" left="1088" top="636" width="196"><label>BEGINNING</label><segs>1090,638,1122,643,1154,654,1186,661,1218,655,1250,644,1283,636,1284,676,1251,680,1218,694,1185,701,1153,693,1120,684,1088,675</segs><pts x="1102" y="661" /><pts x="1122" y="665" /><pts x="1144" y="671" /><pts x="1162" y="675" /><pts x="1180" y="678" /><pts x="1206" y="682" /><pts x="1229" y="675" /><pts x="1248" y="668" /><pts x="1275" y="661" /></box><box height="38" left="1160" top="616" width="61"><label>FOR</label><segs>1160,616,1170,616,1180,616,1190,616,1200,616,1210,616,1220,616,1221,652,1210,652,1200,652,1190,653,1180,653,1170,653,1160,654</segs><pts x="1169" y="639" /><pts x="1188" y="638" /><pts x="1209" y="634" /></box><box height="58" left="1114" top="689" width="154"><label>READERS</label><segs>1116,694,1140,697,1166,703,1191,709,1215,703,1240,694,1265,689,1268,730,1242,734,1216,739,1191,747,1165,742,1139,738,1114,734</segs><pts x="1125" y="714" /><pts x="1146" y="719" /><pts x="1165" y="725" /><pts x="1189" y="728" /><pts x="1210" y="723" /><pts x="1232" y="718" /><pts x="1257" y="709" /></box><box height="18" left="1153" top="798" width="40"><label>T.M</label><segs>1153,798,1159,798,1166,798,1173,798,1179,798,1186,798,1193,798,1192,816,1185,815,1179,815,1173,815,1166,814,1160,814,1154,814</segs><pts x="1160" y="805" /><pts x="1171" y="812" /><pts x="1183" y="807" /></box><box height="44" left="1442" top="610" width="875"><label>Book is sure to find. to his delight. that printed</label><segs>1442,610,1587,610,1733,610,1879,610,2025,610,2171,610,2317,610,2317,654,2171,654,2025,654,1879,654,1733,654,1587,654,1442,654</segs><pts x="1456" y="626" /><pts x="1471" y="628" /><pts x="1502" y="627" /><pts x="1520" y="629" /><pts x="1541" y="627" /><pts x="1557" y="628" /><pts x="1573" y="627" /><pts x="1590" y="629" /><pts x="1606" y="628" /><pts x="1623" y="628" /><pts x="1641" y="627" /><pts x="1655" y="628" /><pts x="1672" y="629" /><pts x="1688" y="629" /><pts x="1705" y="629" /><pts x="1725" y="626" /><pts x="1742" y="627" /><pts x="1758" y="630" /><pts x="1774" y="628" /><pts x="1794" y="629" /><pts x="1808" y="637" /><pts x="1823" y="627" /><pts x="1839" y="630" /><pts x="1853" y="629" /><pts x="1881" y="629" /><pts x="1895" y="632" /><pts x="1913" y="632" /><pts x="1925" y="630" /><pts x="1946" y="632" /><pts x="1962" y="633" /><pts x="1983" y="632" /><pts x="1998" y="632" /><pts x="2009" y="634" /><pts x="2023" y="634" /><pts x="2046" y="630" /><pts x="2064" y="632" /><pts x="2075" y="639" /><pts x="2089" y="632" /><pts x="2105" y="630" /><pts x="2127" y="633" /><pts x="2145" y="635" /><pts x="2164" y="632" /><pts x="2180" y="635" /><pts x="2201" y="636" /><pts x="2217" y="635" /><pts x="2234" y="634" /><pts x="2252" y="634" /><pts x="2272" y="636" /><pts x="2286" y="635" /><pts x="2304" y="633" /></box><box height="83" left="1355" top="2017" width="605"><label>Beginner Books, Inc.</label><segs>1355,2017,1455,2017,1556,2017,1657,2017,1758,2017,1859,2017,1960,2017,1960,2100,1859,2100,1758,2100,1657,2100,1556,2100,1455,2100,1355,2100</segs><pts x="1383" y="2052" /><pts x="1417" y="2064" /><pts x="1451" y="2064" /><pts x="1476" y="2059" /><pts x="1501" y="2059" /><pts x="1535" y="2064" /><pts x="1578" y="2061" /><pts x="1596" y="2061" /><pts x="1630" y="2063" /><pts x="1659" y="2060" /><pts x="1702" y="2064" /><pts x="1739" y="2062" /><pts x="1766" y="2060" /><pts x="1805" y="2063" /><pts x="1824" y="2079" /><pts x="1834" y="2062" /><pts x="1860" y="2061" /><pts x="1889" y="2058" /><pts x="1921" y="2063" /><pts x="1944" y="2076" /></box><box height="65" left="942" top="2108" width="1418"><label>Distributed by RANDOM HOUSE, 457 Madison Ave., New York 22. N.Y.</label><segs>942,2108,1178,2108,1414,2108,1651,2108,1887,2108,2123,2108,2360,2108,2360,2173,2123,2173,1887,2173,1651,2173,1414,2173,1178,2173,942,2173</segs><pts x="968" y="2127" /><pts x="989" y="2135" /><pts x="1000" y="2136" /><pts x="1016" y="2138" /><pts x="1032" y="2136" /><pts x="1051" y="2136" /><pts x="1066" y="2133" /><pts x="1092" y="2133" /><pts x="1108" y="2133" /><pts x="1124" y="2135" /><pts x="1140" y="2136" /><pts x="1161" y="2136" /><pts x="1181" y="2135" /><pts x="1204" y="2136" /><pts x="1225" y="2135" /><pts x="1248" y="2133" /><pts x="1277" y="2133" /><pts x="1312" y="2131" /><pts x="1351" y="2135" /><pts x="1383" y="2135" /><pts x="1424" y="2131" /><pts x="1445" y="2135" /><pts x="1480" y="2131" /><pts x="1505" y="2131" /><pts x="1541" y="2133" /><pts x="1569" y="2129" /><pts x="1606" y="2135" /><pts x="1620" y="2147" /><pts x="1636" y="2136" /><pts x="1651" y="2136" /><pts x="1670" y="2135" /><pts x="1689" y="2133" /><pts x="1714" y="2135" /><pts x="1737" y="2133" /><pts x="1766" y="2140" /><pts x="1791" y="2136" /><pts x="1805" y="2136" /><pts x="1824" y="2140" /><pts x="1838" y="2140" /><pts x="1861" y="2140" /><pts x="1881" y="2140" /><pts x="1902" y="2138" /><pts x="1929" y="2138" /><pts x="1952" y="2138" /><pts x="1962" y="2145" /><pts x="1977" y="2149" /><pts x="1989" y="2142" /><pts x="2009" y="2135" /><pts x="2035" y="2142" /><pts x="2060" y="2136" /><pts x="2087" y="2142" /><pts x="2106" y="2138" /><pts x="2134" y="2140" /><pts x="2154" y="2140" /><pts x="2170" y="2140" /><pts x="2191" y="2140" /><pts x="2207" y="2135" /><pts x="2227" y="2135" /><pts x="2246" y="2153" /><pts x="2257" y="2140" /><pts x="2280" y="2140" /><pts x="2301" y="2147" /><pts x="2322" y="2131" /><pts x="2349" y="2149" /></box><box height="43" left="1437" top="701" width="567"><label>lively, entertaining story as well.</label><segs>1437,701,1531,701,1626,701,1720,701,1815,701,1909,701,2004,701,2004,744,1909,744,1815,744,1720,744,1626,744,1531,744,1437,744</segs><pts x="1443" y="718" /><pts x="1454" y="718" /><pts x="1475" y="720" /><pts x="1490" y="721" /><pts x="1507" y="718" /><pts x="1524" y="721" /><pts x="1536" y="731" /><pts x="1551" y="725" /><pts x="1565" y="723" /><pts x="1587" y="722" /><pts x="1603" y="721" /><pts x="1621" y="722" /><pts x="1638" y="722" /><pts x="1651" y="722" /><pts x="1670" y="724" /><pts x="1685" y="723" /><pts x="1700" y="724" /><pts x="1719" y="725" /><pts x="1733" y="723" /><pts x="1753" y="722" /><pts x="1770" y="723" /><pts x="1784" y="723" /><pts x="1797" y="724" /><pts x="1819" y="724" /><pts x="1838" y="726" /><pts x="1852" y="723" /><pts x="1870" y="726" /><pts x="1887" y="728" /><pts x="1906" y="726" /><pts x="1920" y="727" /><pts x="1939" y="728" /><pts x="1964" y="726" /><pts x="1979" y="725" /><pts x="1990" y="724" /><pts x="1998" y="735" /></box></image></Annotataions>