<Annotataions><image file="0328.jpg"><box height="173" left="2" top="20" width="630"><label>TEAM TAKEDOWN</label><segs>2,138,108,57,214,26,319,20,424,27,528,63,632,150,597,193,507,119,416,88,323,76,230,79,136,108,41,168</segs><pts x="36" y="139" /><pts x="78" y="110" /><pts x="115" y="90" /><pts x="168" y="64" /><pts x="213" y="54" /><pts x="246" y="45" /><pts x="301" y="42" /><pts x="347" y="49" /><pts x="397" y="57" /><pts x="439" y="58" /><pts x="490" y="82" /><pts x="547" y="106" /><pts x="592" y="147" /></box><box height="69" left="213" top="223" width="220"><label>JOHNY</label><segs>213,223,249,224,286,226,323,228,359,229,396,231,433,233,428,292,392,290,356,288,321,286,285,284,249,282,214,280</segs><pts x="231" y="251" /><pts x="261" y="255" /><pts x="301" y="255" /><pts x="351" y="255" /><pts x="398" y="259" /></box><box height="56" left="192" top="298" width="260"><label>BIGG BIGG</label><segs>192,305,235,298,278,299,322,305,365,306,408,307,452,311,451,354,408,353,365,350,323,347,280,342,237,341,195,346</segs><pts x="206" y="321" /><pts x="234" y="319" /><pts x="254" y="315" /><pts x="292" y="317" /><pts x="317" y="323" /><pts x="342" y="324" /><pts x="371" y="325" /><pts x="392" y="329" /><pts x="427" y="330" /></box><box height="57" left="179" top="357" width="287"><label>HENDRICKS</label><segs>179,362,227,357,274,357,322,363,370,366,418,368,466,371,463,414,416,412,369,409,322,406,275,397,228,402,181,404</segs><pts x="196" y="380" /><pts x="231" y="376" /><pts x="258" y="371" /><pts x="287" y="378" /><pts x="325" y="379" /><pts x="350" y="385" /><pts x="369" y="386" /><pts x="402" y="389" /><pts x="444" y="389" /></box></image></Annotataions>