<Annotataions><image file="0361.jpg"><box height="325" left="157" top="267" width="1360"><label>BODY COUNT BAR E GRILL</label><segs>157,553,381,363,607,304,833,267,1060,280,1287,319,1517,535,1398,561,1210,428,1026,400,843,387,660,420,478,442,299,592</segs><pts x="253" y="523" /><pts x="294" y="496" /><pts x="357" y="455" /><pts x="413" y="418" /><pts x="463" y="398" /><pts x="510" y="367" /><pts x="602" y="360" /><pts x="680" y="352" /><pts x="758" y="335" /><pts x="801" y="323" /><pts x="862" y="340" /><pts x="925" y="329" /><pts x="1007" y="329" /><pts x="1066" y="348" /><pts x="1119" y="370" /><pts x="1175" y="355" /><pts x="1216" y="377" /><pts x="1290" y="398" /><pts x="1338" y="426" /><pts x="1372" y="452" /><pts x="1408" y="488" /><pts x="1442" y="515" /></box><box height="92" left="302" top="564" width="1082"><label>FOR EVERY EAR You GET A FREE BEER</label><segs>302,597,482,591,662,586,842,580,1022,575,1202,569,1383,564,1384,624,1203,629,1023,634,843,640,662,645,482,650,302,656</segs><pts x="324" y="620" /><pts x="364" y="622" /><pts x="388" y="626" /><pts x="426" y="630" /><pts x="453" y="619" /><pts x="483" y="620" /><pts x="523" y="620" /><pts x="557" y="624" /><pts x="592" y="624" /><pts x="621" y="614" /><pts x="650" y="614" /><pts x="690" y="618" /><pts x="721" y="622" /><pts x="752" y="611" /><pts x="783" y="607" /><pts x="817" y="611" /><pts x="861" y="614" /><pts x="884" y="608" /><pts x="926" y="607" /><pts x="964" y="611" /><pts x="991" y="610" /><pts x="1021" y="604" /><pts x="1056" y="599" /><pts x="1086" y="599" /><pts x="1113" y="603" /><pts x="1160" y="608" /><pts x="1183" y="610" /><pts x="1223" y="604" /><pts x="1237" y="604" /><pts x="1269" y="599" /><pts x="1306" y="597" /><pts x="1343" y="603" /><pts x="1367" y="603" /></box><box height="63" left="536" top="640" width="618"><label>6 HAI BA TRUNG STREET</label><segs>537,663,639,659,742,655,845,651,948,647,1051,643,1154,640,1154,683,1051,686,948,689,845,693,742,696,639,699,536,703</segs><pts x="554" y="688" /><pts x="585" y="683" /><pts x="614" y="680" /><pts x="653" y="679" /><pts x="676" y="678" /><pts x="692" y="676" /><pts x="719" y="675" /><pts x="750" y="675" /><pts x="782" y="676" /><pts x="811" y="673" /><pts x="833" y="674" /><pts x="868" y="675" /><pts x="902" y="671" /><pts x="945" y="669" /><pts x="974" y="665" /><pts x="1005" y="667" /><pts x="1028" y="665" /><pts x="1052" y="664" /><pts x="1089" y="664" /><pts x="1113" y="661" /><pts x="1141" y="662" /></box><box height="49" left="744" top="697" width="206"><label>SAIGON</label><segs>744,704,777,702,811,701,845,700,878,699,912,698,946,697,950,739,915,740,881,741,847,742,813,743,779,744,745,746</segs><pts x="755" y="725" /><pts x="782" y="722" /><pts x="817" y="725" /><pts x="857" y="724" /><pts x="885" y="719" /><pts x="928" y="719" /></box><box height="44" left="250" top="802" width="399"><label>OWNED + OPERATED</label><segs>255,813,320,811,386,809,452,807,517,805,583,803,649,802,648,836,581,837,515,839,449,841,382,842,316,844,250,846</segs><pts x="266" y="831" /><pts x="300" y="830" /><pts x="327" y="824" /><pts x="351" y="828" /><pts x="375" y="827" /><pts x="401" y="822" /><pts x="423" y="825" /><pts x="437" y="824" /><pts x="467" y="827" /><pts x="492" y="824" /><pts x="517" y="826" /><pts x="540" y="822" /><pts x="563" y="825" /><pts x="587" y="819" /><pts x="608" y="821" /><pts x="631" y="822" /></box><box height="32" left="255" top="853" width="48"><label>BY</label><segs>255,853,263,853,271,853,279,853,287,853,295,853,303,854,303,884,295,884,287,884,279,884,271,884,263,884,256,885</segs><pts x="266" y="870" /><pts x="288" y="867" /></box><box height="41" left="258" top="881" width="258"><label>SEAL TEAM II</label><segs>259,890,301,888,344,887,387,885,429,884,472,882,515,881,516,914,473,915,430,916,387,918,344,919,301,920,258,922</segs><pts x="269" y="908" /><pts x="284" y="907" /><pts x="307" y="908" /><pts x="328" y="908" /><pts x="348" y="907" /><pts x="372" y="904" /><pts x="387" y="904" /><pts x="415" y="907" /><pts x="440" y="903" /><pts x="460" y="900" /><pts x="486" y="904" /><pts x="508" y="897" /></box><box height="51" left="925" top="817" width="490"><label>CALL: PHAN RANG TUOC</label><segs>928,834,1009,831,1090,828,1171,825,1252,822,1333,819,1415,817,1414,848,1332,851,1251,854,1169,858,1088,861,1006,864,925,868</segs><pts x="939" y="848" /><pts x="966" y="849" /><pts x="985" y="847" /><pts x="1005" y="845" /><pts x="1020" y="849" /><pts x="1038" y="847" /><pts x="1079" y="848" /><pts x="1103" y="845" /><pts x="1128" y="842" /><pts x="1151" y="844" /><pts x="1169" y="842" /><pts x="1191" y="841" /><pts x="1220" y="839" /><pts x="1242" y="839" /><pts x="1272" y="839" /><pts x="1297" y="832" /><pts x="1322" y="831" /><pts x="1349" y="833" /><pts x="1373" y="833" /><pts x="1400" y="831" /></box><box height="48" left="926" top="854" width="490"><label>DAILY: 0600-2400 HRS</label><segs>929,870,1010,867,1091,864,1172,862,1253,859,1334,856,1416,854,1415,885,1333,887,1252,890,1170,893,1089,896,1007,899,926,902</segs><pts x="938" y="884" /><pts x="969" y="888" /><pts x="984" y="885" /><pts x="1000" y="885" /><pts x="1018" y="885" /><pts x="1031" y="887" /><pts x="1052" y="889" /><pts x="1093" y="882" /><pts x="1123" y="881" /><pts x="1152" y="881" /><pts x="1182" y="879" /><pts x="1208" y="875" /><pts x="1235" y="872" /><pts x="1260" y="869" /><pts x="1287" y="871" /><pts x="1316" y="870" /><pts x="1341" y="874" /><pts x="1357" y="871" /><pts x="1387" y="868" /><pts x="1406" y="867" /></box></image></Annotataions>