<Annotataions><image file="0582.jpg"><box height="738" left="412" top="290" width="1785"><label>PLAZA</label><segs>412,727,684,529,972,423,1261,319,1562,290,1873,324,2197,425,2028,903,1778,763,1537,719,1298,709,1066,766,838,875,615,1028</segs><pts x="637" y="777" /><pts x="929" y="645" /><pts x="1219" y="529" /><pts x="1570" y="486" /><pts x="1933" y="620" /></box><box height="338" left="509" top="1786" width="2028"><label>THERTRE</label><segs>509,1786,847,1786,1185,1786,1523,1786,1861,1786,2199,1786,2537,1786,2537,2124,2199,2124,1861,2124,1523,2124,1185,2124,847,2124,509,2124</segs><pts x="681" y="1946" /><pts x="927" y="1946" /><pts x="1211" y="1951" /><pts x="1449" y="1956" /><pts x="1756" y="1963" /><pts x="2055" y="1968" /><pts x="2400" y="1948" /></box><box height="1000" left="1200" top="807" width="139"><label>PLAZ</label><segs>1339,833,1335,995,1331,1157,1328,1320,1324,1482,1320,1644,1317,1807,1200,1798,1204,1632,1208,1467,1212,1302,1216,1137,1220,972,1225,807</segs><pts x="1278" y="917" /><pts x="1281" y="1200" /><pts x="1276" y="1435" /><pts x="1272" y="1713" /></box></image></Annotataions>