<Annotataions><image file="0652.jpg"><box height="167" left="128" top="74" width="439"><label>and their</label><segs>128,204,198,125,270,74,343,75,417,76,491,118,567,191,509,233,452,181,395,158,339,148,284,160,229,192,175,241</segs><pts x="165" y="204" /><pts x="201" y="149" /><pts x="264" y="121" /><pts x="300" y="110" /><pts x="342" y="107" /><pts x="396" y="110" /><pts x="445" y="140" /><pts x="490" y="167" /><pts x="513" y="198" /></box><box height="271" left="78" top="335" width="284"><label>network's</label><segs>125,335,148,387,182,428,205,481,247,512,308,520,362,538,354,606,283,591,221,566,167,532,129,482,93,428,78,353</segs><pts x="122" y="373" /><pts x="133" y="412" /><pts x="148" y="445" /><pts x="174" y="482" /><pts x="205" y="519" /><pts x="236" y="538" /><pts x="274" y="552" /><pts x="307" y="537" /><pts x="331" y="570" /></box><box height="255" left="366" top="350" width="249"><label>network</label><segs>366,539,413,525,446,498,488,479,514,445,515,390,534,350,615,368,585,416,562,471,531,518,491,556,437,580,384,605</segs><pts x="397" y="562" /><pts x="444" y="542" /><pts x="464" y="524" /><pts x="505" y="495" /><pts x="534" y="458" /><pts x="545" y="425" /><pts x="558" y="387" /></box></image></Annotataions>