<Annotataions><image file="0693.jpg"><box height="189" left="356" top="326" width="796"><label>ENGLISH HERITAGE</label><segs>356,467,488,373,621,328,754,326,887,328,1019,371,1152,469,1109,515,989,459,870,403,751,399,631,407,511,442,392,510</segs><pts x="393" y="468" /><pts x="439" y="432" /><pts x="489" y="411" /><pts x="533" y="393" /><pts x="573" y="378" /><pts x="607" y="371" /><pts x="663" y="359" /><pts x="718" y="358" /><pts x="794" y="355" /><pts x="846" y="362" /><pts x="895" y="374" /><pts x="934" y="383" /><pts x="971" y="395" /><pts x="1011" y="415" /><pts x="1060" y="442" /><pts x="1106" y="476" /></box><box height="148" left="394" top="613" width="758"><label>GEOFFREY</label><segs>399,613,524,614,650,615,775,616,901,617,1026,618,1152,620,1081,761,966,758,852,756,737,754,623,752,508,750,394,748</segs><pts x="464" y="693" /><pts x="551" y="689" /><pts x="642" y="687" /><pts x="733" y="690" /><pts x="798" y="694" /><pts x="863" y="694" /><pts x="971" y="698" /><pts x="1061" y="688" /></box><box height="114" left="478" top="875" width="579"><label>1882-1965</label><segs>1057,875,960,876,864,877,767,878,671,879,574,880,478,881,478,989,573,988,669,988,765,988,861,987,957,987,1053,987</segs><pts x="512" y="923" /><pts x="561" y="924" /><pts x="627" y="927" /><pts x="708" y="932" /><pts x="760" y="932" /><pts x="813" y="930" /><pts x="855" y="928" /><pts x="918" y="928" /><pts x="989" y="920" /></box><box height="127" left="396" top="1087" width="722"><label>lived here</label><segs>399,1087,518,1091,638,1095,758,1100,878,1104,998,1108,1118,1113,1079,1214,965,1213,851,1212,737,1211,623,1210,509,1209,396,1208</segs><pts x="454" y="1140" /><pts x="498" y="1153" /><pts x="555" y="1154" /><pts x="624" y="1155" /><pts x="701" y="1155" /><pts x="775" y="1155" /><pts x="843" y="1152" /><pts x="913" y="1153" /><pts x="972" y="1150" /><pts x="1048" y="1157" /></box><box height="120" left="457" top="1199" width="594"><label>1909~1910</label><segs>457,1206,556,1204,655,1203,754,1202,853,1201,952,1200,1051,1199,1010,1306,917,1308,825,1310,733,1312,641,1314,549,1316,457,1319</segs><pts x="519" y="1251" /><pts x="576" y="1257" /><pts x="637" y="1254" /><pts x="698" y="1257" /><pts x="762" y="1257" /><pts x="809" y="1250" /><pts x="861" y="1254" /><pts x="918" y="1262" /><pts x="970" y="1259" /></box><box height="122" left="632" top="512" width="235"><label>SIR</label><segs>641,515,672,514,704,514,735,513,767,513,798,512,830,512,867,624,827,625,788,627,749,629,710,630,671,632,632,634</segs><pts x="684" y="568" /><pts x="732" y="567" /><pts x="783" y="568" /></box><box height="131" left="154" top="973" width="1203"><label>Aircraft designer</label><segs>189,973,383,978,578,984,773,989,967,995,1162,1000,1357,1006,1322,1104,1127,1103,932,1102,738,1101,543,1100,348,1099,154,1098</segs><pts x="232" y="1031" /><pts x="313" y="1031" /><pts x="366" y="1043" /><pts x="432" y="1046" /><pts x="492" y="1052" /><pts x="563" y="1054" /><pts x="623" y="1036" /><pts x="696" y="1045" /><pts x="761" y="1048" /><pts x="814" y="1048" /><pts x="898" y="1043" /><pts x="969" y="1048" /><pts x="1021" y="1051" /><pts x="1069" y="1045" /><pts x="1152" y="1057" /><pts x="1236" y="1048" /><pts x="1304" y="1049" /></box><box height="122" left="166" top="755" width="1183"><label>DE HAVILLAND</label><segs>168,758,363,757,558,757,753,756,948,756,1143,755,1338,755,1349,874,1151,874,954,875,757,875,560,876,363,876,166,877</segs><pts x="228" y="818" /><pts x="322" y="810" /><pts x="418" y="811" /><pts x="504" y="807" /><pts x="628" y="811" /><pts x="713" y="818" /><pts x="798" y="813" /><pts x="846" y="811" /><pts x="934" y="816" /><pts x="1041" y="810" /><pts x="1170" y="808" /><pts x="1264" y="811" /></box></image></Annotataions>