<Annotataions><image file="0756.jpg"><box top="777" left="355" width="547" height="322"><label>PilsnerUrquell</label><segs>363,919,450,895,538,871,626,848,714,824,802,800,890,777,902,949,810,974,719,999,628,1024,537,1049,446,1074,355,1099</segs><pts x="418" y="978" /><pts x="455" y="988" /><pts x="476" y="981" /><pts x="498" y="974" /><pts x="533" y="963" /><pts x="568" y="951" /><pts x="601" y="943" /><pts x="659" y="909" /><pts x="694" y="911" /><pts x="730" y="908" /><pts x="774" y="903" /><pts x="814" y="896" /><pts x="840" y="886" /><pts x="867" y="884" /></box><box top="1349" left="363" width="474" height="137"><label>BEER PUB</label><segs>371,1406,448,1396,526,1387,604,1377,681,1368,759,1358,837,1349,832,1437,753,1445,675,1453,597,1461,519,1469,441,1477,363,1486</segs><pts x="406" y="1440" /><pts x="462" y="1434" /><pts x="510" y="1428" /><pts x="560" y="1422" /><pts x="607" y="1421" /><pts x="656" y="1415" /><pts x="723" y="1408" /><pts x="797" y="1399" /></box><box top="1470" left="339" width="496" height="139"><label>KRISTIAN</label><segs>347,1521,428,1512,509,1504,591,1495,672,1487,753,1478,835,1470,835,1558,752,1566,669,1575,587,1583,504,1592,421,1600,339,1609</segs><pts x="387" y="1560" /><pts x="453" y="1556" /><pts x="503" y="1549" /><pts x="543" y="1547" /><pts x="597" y="1543" /><pts x="649" y="1538" /><pts x="706" y="1532" /><pts x="783" y="1524" /></box><box top="1144" left="423" width="379" height="100"><label>PLZEN. CZECH</label><segs>425,1203,487,1193,550,1183,613,1173,676,1163,739,1153,802,1144,802,1187,738,1196,675,1206,612,1215,549,1225,486,1234,423,1244</segs><pts x="443" y="1220" /><pts x="474" y="1213" /><pts x="507" y="1210" /><pts x="539" y="1206" /><pts x="571" y="1203" /><pts x="606" y="1207" /><pts x="619" y="1198" /><pts x="645" y="1189" /><pts x="676" y="1187" /><pts x="707" y="1181" /><pts x="744" y="1177" /><pts x="777" y="1172" /></box><box top="1208" left="476" width="268" height="61"><label>THE ORIGINAL PILSNER</label><segs>476,1248,520,1241,565,1234,610,1228,654,1221,699,1214,744,1208,744,1232,699,1238,654,1244,610,1250,565,1256,520,1262,476,1269</segs><pts x="486" y="1259" /><pts x="501" y="1255" /><pts x="514" y="1253" /><pts x="524" y="1251" /><pts x="536" y="1251" /><pts x="550" y="1249" /><pts x="563" y="1248" /><pts x="576" y="1245" /><pts x="587" y="1244" /><pts x="601" y="1242" /><pts x="617" y="1240" /><pts x="631" y="1238" /><pts x="641" y="1237" /><pts x="653" y="1235" /><pts x="662" y="1233" /><pts x="674" y="1231" /><pts x="687" y="1228" /><pts x="703" y="1227" /><pts x="717" y="1226" /><pts x="731" y="1224" /></box><box top="1115" left="512" width="198" height="71"><label>Brewed in</label><segs>525,1142,555,1137,586,1133,617,1128,648,1124,679,1119,710,1115,706,1159,673,1163,641,1168,609,1172,576,1177,544,1181,512,1186</segs><pts x="544" y="1158" /><pts x="558" y="1159" /><pts x="578" y="1159" /><pts x="605" y="1155" /><pts x="626" y="1151" /><pts x="646" y="1148" /><pts x="660" y="1145" /><pts x="674" y="1144" /><pts x="691" y="1142" /></box><box top="710" left="465" width="150" height="87"><label>PLZENSKY PRAZDROI</label><segs>465,795,481,749,504,730,527,716,552,710,578,712,615,765,596,774,569,741,548,735,529,738,512,749,496,767,483,797</segs><pts x="476" y="786" /><pts x="480" y="776" /><pts x="486" y="766" /><pts x="492" y="757" /><pts x="503" y="745" /><pts x="512" y="736" /><pts x="522" y="729" /><pts x="535" y="724" /><pts x="542" y="723" /><pts x="550" y="721" /><pts x="562" y="722" /><pts x="575" y="724" /><pts x="582" y="729" /><pts x="589" y="736" /><pts x="595" y="747" /><pts x="598" y="755" /><pts x="601" y="766" /></box><box top="802" left="469" width="131" height="60"><label>OD ROKU 1842</label><segs>485,816,504,837,521,839,538,837,554,828,569,815,584,802,600,815,581,835,561,849,540,858,518,862,494,857,469,840</segs><pts x="483" y="832" /><pts x="490" y="838" /><pts x="498" y="843" /><pts x="505" y="847" /><pts x="516" y="849" /><pts x="526" y="849" /><pts x="540" y="847" /><pts x="548" y="844" /><pts x="556" y="840" /><pts x="567" y="832" /><pts x="576" y="825" /><pts x="584" y="816" /></box><box top="1824" left="278" width="202" height="107"><label>MUSIC CENTRE SLOVAKIA</label><segs>278,1824,312,1837,349,1847,383,1860,418,1873,451,1890,480,1917,478,1931,447,1910,415,1891,382,1875,347,1864,312,1852,279,1837</segs><pts x="286" y="1834" /><pts x="301" y="1838" /><pts x="316" y="1844" /><pts x="326" y="1848" /><pts x="338" y="1853" /><pts x="350" y="1859" /><pts x="361" y="1861" /><pts x="372" y="1864" /><pts x="383" y="1870" /><pts x="395" y="1873" /><pts x="405" y="1878" /><pts x="415" y="1882" /><pts x="423" y="1888" /><pts x="431" y="1892" /><pts x="438" y="1895" /><pts x="446" y="1899" /><pts x="453" y="1904" /><pts x="460" y="1910" /><pts x="466" y="1914" /><pts x="471" y="1917" /><pts x="476" y="1921" /></box><box top="1775" left="276" width="217" height="136"><label>hudobne' entrum</label><segs>282,1775,319,1787,355,1800,394,1810,427,1831,460,1851,493,1873,483,1911,452,1886,418,1869,383,1853,347,1839,312,1824,276,1812</segs><pts x="290" y="1803" /><pts x="307" y="1807" /><pts x="321" y="1812" /><pts x="336" y="1821" /><pts x="351" y="1824" /><pts x="366" y="1831" /><pts x="381" y="1835" /><pts x="385" y="1820" /><pts x="408" y="1843" /><pts x="434" y="1859" /><pts x="445" y="1866" /><pts x="452" y="1870" /><pts x="458" y="1874" /><pts x="466" y="1880" /><pts x="475" y="1888" /></box></image></Annotataions>